Workbook

Sheet How to use
B2: Free family budget template
B3: From Budget Famille: budgetfamille.com/en
B5: How to use it
B6: 1. “Monthly budget” tab: replace the amounts in the yellow cells with yours (take-home pay, bills, savings).
B7: 2. “Joint pot” tab: if you’re a couple, compare the 3 ways to split (50/50, in proportion to income, same spending money).
B8: 3. “Year” tab: add the bills that come once a year (property tax, car insurance…) in the yellow column of the right month.
B10: Key
B11: Yellow cells: fill in with your numbers (the amounts already there are an example: Alex and Sam).
B12: Green text: value taken from another tab. Black text: automatic calculation, don’t change it.
B14: Words to know
B15: Joint pot: the money each person pays in to cover the household’s bills and shared savings.
B16: Spending money: what each person has left after their share of the joint pot, to spend as they like.
... B20: Budget Famille does the same automatically every month, for free: https://www.budgetfamille.com/en

Sheet Monthly budget
B2: Monthly budget
B3: Replace the yellow cells with your amounts. Totals work themselves out.
B5: Income | C5: Monthly amount | D5: Note
B6: Take-home pay: person 1 | C6: 2800 | D6: Example: Alex
B7: Take-home pay: person 2 | C7: 2100 | D7: Example: Sam. Enter 0 if you’re on your own.
B8: Other income | C8: 150 | D8: Benefits, bonuses, rental income…
B9: Total income | C9: =SUM(C6:C8)
B11: Household bills | C11: Monthly amount | D11: Note
B12: Housing (rent or mortgage) | C12: 1150
B13: Energy (electricity, gas) | C13: 110
B14: Water | C14: 30
B15: Internet and phones | C15: 55
B16: Insurance (home, car, health) | C16: 140
B17: Groceries | C17: 520
B18: Transport (fuel, public transport) | C18: 160
B19: Children (school meals, childcare, activities) | C19: 120
B20: Subscriptions (streaming, gym…) | C20: 35
B21: Taxes (monthly share) | C21: 90 | D21: Yearly property tax: see the Year tab
B22: Health (out of pocket) | C22: 30
B23: Fun and going out | C23: 120
B24: Other | C24: 60
B25: Total bills | C25: =SUM(C12:C24)
B27: Savings | C27: Monthly amount | D27: Note
B28: Emergency fund | C28: 150 | D28: Usual target: 3 to 6 months of bills
B29: Holidays | C29: 150
B30: Goal (down payment, car…) | C30: 100
B31: Total savings | C31: =SUM(C28:C30)
B33: Summary
B34: Income | C34: =C9
B35: Bills | C35: =C25
B36: Savings | C36: =C31
B37: Left for the month | C37: =C9-C25-C31 | D37: Everyone’s spending money included. Negative: money is short this month.
B38: Share of income saved | C38: =IF(C9>0,C31/C9,0) | D38: Common benchmark: aim for 10 to 20% of income.

Sheet Joint pot
B2: Joint pot: who pays in how much?
B3: Pay and needs come from the “Monthly budget” tab.
B5: Take-home pay: person 1 | C5: ='Monthly budget'!C6
B6: Take-home pay: person 2 | C6: ='Monthly budget'!C7
B7: Needed this month (bills + savings) | C7: ='Monthly budget'!C25+'Monthly budget'!C31
B9: Method | C9: Pays in: person 1 | D9: Pays in: person 2 | E9: Spending money 1 | F9: Spending money 2 | G9: Spending money gap
B10: Equal shares (50/50) | C10: =C7/2 | D10: =C7/2 | E10: =C5-C10 | F10: =C6-D10 | G10: =ABS(E10-F10)
B11: In proportion to pay | C11: =IF(C5+C6>0,C7*C5/(C5+C6),C7/2) | D11: =IF(C5+C6>0,C7*C6/(C5+C6),C7/2) | E11: =C5-C11 | F11: =C6-D11 | G11: =ABS(E11-F11)
B12: Same spending money | C12: =MAX(0,MIN(C7,(C5-C6+C7)/2)) | D12: =C7-C12 | E12: =C5-C12 | F12: =C6-D12 | G12: =ABS(E12-F12)
B14: 50/50: each pays in the same amount; spending money follows the pay gap.
B15: In proportion: each pays in the same share of their pay; the most common method when incomes differ.
B16: Same spending money: each keeps the same amount for themselves (if the pay gap is larger than the need, the higher earner pays it all).

Sheet Year
B2: My year
B3: Each month starts from the monthly budget. Add in yellow what doesn’t come every month.
B5: Month | C5: Income | D5: Extra income | E5: Bills | F5: Extra bills | G5: Savings | H5: Left for the month | I5: Running total
B6: January | C6: ='Monthly budget'!$C$9 | D6: 0 | E6: ='Monthly budget'!$C$25 | F6: 0 | G6: ='Monthly budget'!$C$31 | H6: =C6+D6-E6-F6-G6 | I6: =H6
B7: February | C7: ='Monthly budget'!$C$9 | D7: 0 | E7: ='Monthly budget'!$C$25 | F7: 0 | G7: ='Monthly budget'!$C$31 | H7: =C7+D7-E7-F7-G7 | I7: =I6+H7
B8: March | C8: ='Monthly budget'!$C$9 | D8: 0 | E8: ='Monthly budget'!$C$25 | F8: 0 | G8: ='Monthly budget'!$C$31 | H8: =C8+D8-E8-F8-G8 | I8: =I7+H8
B9: April | C9: ='Monthly budget'!$C$9 | D9: 0 | E9: ='Monthly budget'!$C$25 | F9: 0 | G9: ='Monthly budget'!$C$31 | H9: =C9+D9-E9-F9-G9 | I9: =I8+H9
B10: May | C10: ='Monthly budget'!$C$9 | D10: 0 | E10: ='Monthly budget'!$C$25 | F10: 0 | G10: ='Monthly budget'!$C$31 | H10: =C10+D10-E10-F10-G10 | I10: =I9+H10
B11: June | C11: ='Monthly budget'!$C$9 | D11: 300 | E11: ='Monthly budget'!$C$25 | F11: 0 | G11: ='Monthly budget'!$C$31 | H11: =C11+D11-E11-F11-G11 | I11: =I10+H11
B12: July | C12: ='Monthly budget'!$C$9 | D12: 0 | E12: ='Monthly budget'!$C$25 | F12: 0 | G12: ='Monthly budget'!$C$31 | H12: =C12+D12-E12-F12-G12 | I12: =I11+H12
B13: August | C13: ='Monthly budget'!$C$9 | D13: 0 | E13: ='Monthly budget'!$C$25 | F13: 0 | G13: ='Monthly budget'!$C$31 | H13: =C13+D13-E13-F13-G13 | I13: =I12+H13
B14: September | C14: ='Monthly budget'!$C$9 | D14: 0 | E14: ='Monthly budget'!$C$25 | F14: 0 | G14: ='Monthly budget'!$C$31 | H14: =C14+D14-E14-F14-G14 | I14: =I13+H14
B15: October | C15: ='Monthly budget'!$C$9 | D15: 0 | E15: ='Monthly budget'!$C$25 | F15: 980 | G15: ='Monthly budget'!$C$31 | H15: =C15+D15-E15-F15-G15 | I15: =I14+H15
B16: November | C16: ='Monthly budget'!$C$9 | D16: 0 | E16: ='Monthly budget'!$C$25 | F16: 0 | G16: ='Monthly budget'!$C$31 | H16: =C16+D16-E16-F16-G16 | I16: =I15+H16
B17: December | C17: ='Monthly budget'!$C$9 | D17: 0 | E17: ='Monthly budget'!$C$25 | F17: 0 | G17: ='Monthly budget'!$C$31 | H17: =C17+D17-E17-F17-G17 | I17: =I16+H17
B18: Total | C18: =SUM(C6:C17) | D18: =SUM(D6:D17) | E18: =SUM(E6:E17) | F18: =SUM(F6:F17) | G18: =SUM(G6:G17) | H18: =SUM(H6:H17)
B20: Saved over the year | F20: =G18
