Workbook

Sheet Mode d'emploi
B2: Tableau de budget familial gratuit
B3: Proposé par Budget Famille — budgetfamille.com
B5: Comment l'utiliser
B6: 1. Onglet « Budget du mois » : remplacez les montants des cases jaunes par les vôtres (salaires nets, charges, épargne).
B7: 2. Onglet « Pot commun » : si vous êtes en couple, comparez les 3 façons de répartir (50/50, au prorata, même argent de poche).
B8: 3. Onglet « Année » : ajoutez les charges qui ne tombent qu'une fois (taxe foncière, assurance auto…) dans la colonne jaune du bon mois.
B10: Légende
B11: Cases jaunes : à remplir avec vos chiffres (les montants présents sont un exemple : Camille et Mehdi).
B12: Texte vert : valeur reprise d'un autre onglet. Texte noir : calcul automatique, à ne pas modifier.
B14: Les mots à connaître
B15: Pot commun : l'argent que chacun verse pour payer les charges du foyer et l'épargne commune.
B16: Argent de poche : ce qui reste à chacun après sa part du pot commun. Il en fait ce qu'il veut.
... B20: Budget Famille fait la même chose automatiquement chaque mois, gratuitement : https://www.budgetfamille.com/signup

Sheet Budget du mois
B2: Budget du mois
B3: Remplacez les cases jaunes par vos montants. Les totaux se calculent seuls.
B5: Revenus | C5: Montant mensuel | D5: Note
B6: Salaire net — personne 1 | C6: 2800 | D6: Exemple : Camille
B7: Salaire net — personne 2 | C7: 2100 | D7: Exemple : Mehdi. Mettez 0 si vous êtes seul.
B8: Autres revenus | C8: 150 | D8: Allocations, primes, revenus locatifs…
B9: Total des revenus | C9: =SUM(C6:C8) -> 5050
B11: Charges du foyer | C11: Montant mensuel | D11: Note
B12: Logement (loyer ou crédit) | C12: 1150
B13: Énergie (électricité, gaz) | C13: 110
B14: Eau | C14: 30
B15: Internet et téléphones | C15: 55
B16: Assurances (habitation, auto, santé) | C16: 140
B17: Courses | C17: 520
B18: Transport (carburant, transports en commun) | C18: 160
B19: Enfants (cantine, garde, activités) | C19: 120
B20: Abonnements (streaming, sport…) | C20: 35
B21: Impôts et taxes (mensualisés) | C21: 90 | D21: Taxe foncière annuelle : voir l’onglet Année
B22: Santé (hors remboursements) | C22: 30
B23: Loisirs et sorties | C23: 120
B24: Divers | C24: 60
B25: Total des charges | C25: =SUM(C12:C24) -> 2620
B27: Épargne | C27: Montant mensuel | D27: Note
B28: Fonds d’urgence | C28: 150 | D28: Objectif conseillé : 3 à 6 mois de charges
B29: Vacances | C29: 150
B30: Projet (apport, voiture…) | C30: 100
B31: Total de l’épargne | C31: =SUM(C28:C30) -> 400
B33: Synthèse
B34: Revenus | C34: =C9 -> 5050
B35: Charges | C35: =C25 -> 2620
B36: Épargne | C36: =C31 -> 400
B37: Reste du mois | C37: =C9-C25-C31 -> 2030 | D37: L’argent de poche de chacun compris. Négatif : il manque de l’argent ce mois-ci.
B38: Part des revenus épargnée | C38: =IF(C9>0,C31/C9,0) -> 0.079207921 | D38: Repère courant : viser 10 à 20 % des revenus.

Sheet Pot commun
B2: Pot commun : qui verse combien ?
B3: Les salaires et le besoin viennent de l’onglet « Budget du mois ».
B5: Salaire net — personne 1 | C5: ='Budget du mois'!C6 -> 2800
B6: Salaire net — personne 2 | C6: ='Budget du mois'!C7 -> 2100
B7: Besoin du mois (charges + épargne) | C7: ='Budget du mois'!C25+'Budget du mois'!C31 -> 3020
B9: Méthode | C9: Verse — personne 1 | D9: Verse — personne 2 | E9: Argent de poche 1 | F9: Argent de poche 2 | G9: Écart d’argent de poche
B10: À parts égales (50/50) | C10: =C7/2 -> 1510 | D10: =C7/2 -> 1510 | E10: =C5-C10 -> 1290 | F10: =C6-D10 -> 590 | G10: =ABS(E10-F10) -> 700
B11: Au prorata des salaires | C11: =IF(C5+C6>0,C7*C5/(C5+C6),C7/2) -> 1725.7143 | D11: =IF(C5+C6>0,C7*C6/(C5+C6),C7/2) -> 1294.2857 | E11: =C5-C11 -> 1074.2857 | F11: =C6-D11 -> 805.71429 | G11: =ABS(E11-F11) -> 268.57143
B12: Même argent de poche | C12: =MAX(0,MIN(C7,(C5-C6+C7)/2)) -> 1860 | D12: =C7-C12 -> 1160 | E12: =C5-C12 -> 940 | F12: =C6-D12 -> 940 | G12: =ABS(E12-F12) -> 0
B14: 50/50 : chacun verse la même somme ; l’argent de poche suit l’écart de salaires.
B15: Prorata : chacun verse la même part de son salaire ; c’est la méthode la plus courante quand les revenus sont différents.
B16: Même argent de poche : chacun garde la même somme pour lui (si l’écart de salaires dépasse le besoin, le plus haut salaire paie tout).

Sheet Année
B2: Mon année
B3: Chaque mois reprend le budget du mois. Ajoutez en jaune ce qui ne revient pas tous les mois.
B5: Mois | C5: Revenus | D5: Revenus en plus | E5: Charges | F5: Charges en plus | G5: Épargne | H5: Reste du mois | I5: Reste cumulé
B6: Janvier | C6: ='Budget du mois'!$C$9 -> 5050 | D6: 0 | E6: ='Budget du mois'!$C$25 -> 2620 | F6: 0 | G6: ='Budget du mois'!$C$31 -> 400 | H6: =C6+D6-E6-F6-G6 -> 2030 | I6: =H6 -> 2030
B7: Février | C7: ='Budget du mois'!$C$9 -> 5050 | D7: 0 | E7: ='Budget du mois'!$C$25 -> 2620 | F7: 0 | G7: ='Budget du mois'!$C$31 -> 400 | H7: =C7+D7-E7-F7-G7 -> 2030 | I7: =I6+H7 -> 4060
B8: Mars | C8: ='Budget du mois'!$C$9 -> 5050 | D8: 0 | E8: ='Budget du mois'!$C$25 -> 2620 | F8: 0 | G8: ='Budget du mois'!$C$31 -> 400 | H8: =C8+D8-E8-F8-G8 -> 2030 | I8: =I7+H8 -> 6090
B9: Avril | C9: ='Budget du mois'!$C$9 -> 5050 | D9: 0 | E9: ='Budget du mois'!$C$25 -> 2620 | F9: 0 | G9: ='Budget du mois'!$C$31 -> 400 | H9: =C9+D9-E9-F9-G9 -> 2030 | I9: =I8+H9 -> 8120
B10: Mai | C10: ='Budget du mois'!$C$9 -> 5050 | D10: 0 | E10: ='Budget du mois'!$C$25 -> 2620 | F10: 0 | G10: ='Budget du mois'!$C$31 -> 400 | H10: =C10+D10-E10-F10-G10 -> 2030 | I10: =I9+H10 -> 10150
B11: Juin | C11: ='Budget du mois'!$C$9 -> 5050 | D11: 300 | E11: ='Budget du mois'!$C$25 -> 2620 | F11: 0 | G11: ='Budget du mois'!$C$31 -> 400 | H11: =C11+D11-E11-F11-G11 -> 2330 | I11: =I10+H11 -> 12480
B12: Juillet | C12: ='Budget du mois'!$C$9 -> 5050 | D12: 0 | E12: ='Budget du mois'!$C$25 -> 2620 | F12: 0 | G12: ='Budget du mois'!$C$31 -> 400 | H12: =C12+D12-E12-F12-G12 -> 2030 | I12: =I11+H12 -> 14510
B13: Août | C13: ='Budget du mois'!$C$9 -> 5050 | D13: 0 | E13: ='Budget du mois'!$C$25 -> 2620 | F13: 0 | G13: ='Budget du mois'!$C$31 -> 400 | H13: =C13+D13-E13-F13-G13 -> 2030 | I13: =I12+H13 -> 16540
B14: Septembre | C14: ='Budget du mois'!$C$9 -> 5050 | D14: 0 | E14: ='Budget du mois'!$C$25 -> 2620 | F14: 0 | G14: ='Budget du mois'!$C$31 -> 400 | H14: =C14+D14-E14-F14-G14 -> 2030 | I14: =I13+H14 -> 18570
B15: Octobre | C15: ='Budget du mois'!$C$9 -> 5050 | D15: 0 | E15: ='Budget du mois'!$C$25 -> 2620 | F15: 980 | G15: ='Budget du mois'!$C$31 -> 400 | H15: =C15+D15-E15-F15-G15 -> 1050 | I15: =I14+H15 -> 19620
B16: Novembre | C16: ='Budget du mois'!$C$9 -> 5050 | D16: 0 | E16: ='Budget du mois'!$C$25 -> 2620 | F16: 0 | G16: ='Budget du mois'!$C$31 -> 400 | H16: =C16+D16-E16-F16-G16 -> 2030 | I16: =I15+H16 -> 21650
B17: Décembre | C17: ='Budget du mois'!$C$9 -> 5050 | D17: 0 | E17: ='Budget du mois'!$C$25 -> 2620 | F17: 0 | G17: ='Budget du mois'!$C$31 -> 400 | H17: =C17+D17-E17-F17-G17 -> 2030 | I17: =I16+H17 -> 23680
B18: Total | C18: =SUM(C6:C17) -> 60600 | D18: =SUM(D6:D17) -> 300 | E18: =SUM(E6:E17) -> 31440 | F18: =SUM(F6:F17) -> 980 | G18: =SUM(G6:G17) -> 4800 | H18: =SUM(H6:H17) -> 23680
B20: Épargné sur l’année | F20: =G18 -> 4800
